nonebot_plugin_summary_group/Config.py
nonebot_plugin_summary_group/Model.py
nonebot_plugin_summary_group/Store.py
nonebot_plugin_summary_group/__init__.py
nonebot_plugin_summary_group/assert/github-markdown-dark.css
nonebot_plugin_summary_group/utils/queue_request.py
nonebot_plugin_summary_group/utils/utils.py
nonebot_plugin_summary_group-0.8.0.dist-info/licenses/LICENSE
nonebot_plugin_summary_group-0.8.0.dist-info/METADATA
nonebot_plugin_summary_group-0.8.0.dist-info/WHEEL
nonebot_plugin_summary_group-0.8.0.dist-info/top_level.txt
nonebot_plugin_summary_group-0.8.0.dist-info/RECORD
