Metadata-Version: 2.4
Name: nonebot-plugin-summary-group
Version: 0.8.0
Summary: 基于 Nonebot2，使用 AI 分析群聊记录，生成讨论内容的总结。
Author-email: StillMisty <1772797842@qq.com>
License:                                  Apache License
Project-URL: Homepage, https://github.com/StillMisty/nonebot_plugin_summary_group
Keywords: nonebot2,nonebot,plugin,summary,AI,group-chat
Classifier: Programming Language :: Python :: 3
Classifier: Programming Language :: Python :: 3.10
Classifier: Programming Language :: Python :: 3.11
Classifier: Programming Language :: Python :: 3.12
Classifier: Programming Language :: Python :: 3.13
Classifier: License :: OSI Approved :: Apache Software License
Classifier: Operating System :: OS Independent
Classifier: Topic :: Communications :: Chat
Requires-Python: >=3.10
License-File: LICENSE
Requires-Dist: httpx>=0.27
Requires-Dist: nonebot-adapter-onebot>=2.3
Requires-Dist: nonebot2>=2.3
Requires-Dist: nonebot_plugin_alconna>=0.53
Requires-Dist: nonebot_plugin_localstore>=0.7
Requires-Dist: nonebot_plugin_apscheduler>=0.5
Dynamic: license-file
